{"namedChunkGroups":{"polyfill":{"name":"polyfill","assets":[{"name":"webpack-runtime-a9e8b7badfb654e0e8a6.js","size":4935},{"name":"polyfill-a3860cbf14b9692d8834.js","size":82188}],"filteredAssets":0,"assetsSize":87123,"filteredAuxiliaryAssets":0,"auxiliaryAssetsSize":0},"app":{"name":"app","assets":[{"name":"webpack-runtime-a9e8b7badfb654e0e8a6.js","size":4935},{"name":"styles.1a1552db057571bb49a3.css","size":371008},{"name":"styles-e4fcbea169887e6398e3.js","size":8124589},{"name":"app-0df6be084b96cb872eb8.js","size":2553544}],"filteredAssets":0,"assetsSize":11054076,"filteredAuxiliaryAssets":2,"auxiliaryAssetsSize":123816},"component---gatsby-theme-gogocode-site-pages-404-tsx":{"name":"component---gatsby-theme-gogocode-site-pages-404-tsx","assets":[{"name":"styles.1a1552db057571bb49a3.css","size":371008},{"name":"styles-e4fcbea169887e6398e3.js","size":8124589}],"filteredAssets":0,"assetsSize":8495597,"filteredAuxiliaryAssets":2,"auxiliaryAssetsSize":123816},"component---gatsby-theme-gogocode-site-pages-index-tsx":{"name":"component---gatsby-theme-gogocode-site-pages-index-tsx","assets":[{"name":"styles.1a1552db057571bb49a3.css","size":371008},{"name":"styles-e4fcbea169887e6398e3.js","size":8124589}],"filteredAssets":0,"assetsSize":8495597,"filteredAuxiliaryAssets":2,"auxiliaryAssetsSize":123816},"component---gatsby-theme-gogocode-site-templates-document-tsx":{"name":"component---gatsby-theme-gogocode-site-templates-document-tsx","assets":[{"name":"styles.1a1552db057571bb49a3.css","size":371008},{"name":"styles-e4fcbea169887e6398e3.js","size":8124589}],"filteredAssets":0,"assetsSize":8495597,"filteredAuxiliaryAssets":2,"auxiliaryAssetsSize":123816},"component---site-pages-independent-en-tsx":{"name":"component---site-pages-independent-en-tsx","assets":[{"name":"styles.1a1552db057571bb49a3.css","size":371008},{"name":"styles-e4fcbea169887e6398e3.js","size":8124589}],"filteredAssets":0,"assetsSize":8495597,"filteredAuxiliaryAssets":2,"auxiliaryAssetsSize":123816},"component---site-pages-independent-zh-tsx":{"name":"component---site-pages-independent-zh-tsx","assets":[{"name":"styles.1a1552db057571bb49a3.css","size":371008},{"name":"styles-e4fcbea169887e6398e3.js","size":8124589}],"filteredAssets":0,"assetsSize":8495597,"filteredAuxiliaryAssets":2,"auxiliaryAssetsSize":123816},"component---site-pages-index-en-tsx":{"name":"component---site-pages-index-en-tsx","assets":[{"name":"styles.1a1552db057571bb49a3.css","size":371008},{"name":"styles-e4fcbea169887e6398e3.js","size":8124589}],"filteredAssets":0,"assetsSize":8495597,"filteredAuxiliaryAssets":2,"auxiliaryAssetsSize":123816},"component---site-pages-index-zh-tsx":{"name":"component---site-pages-index-zh-tsx","assets":[{"name":"styles.1a1552db057571bb49a3.css","size":371008},{"name":"styles-e4fcbea169887e6398e3.js","size":8124589}],"filteredAssets":0,"assetsSize":8495597,"filteredAuxiliaryAssets":2,"auxiliaryAssetsSize":123816}},"assetsByChunkName":{"polyfill":["webpack-runtime-a9e8b7badfb654e0e8a6.js","polyfill-a3860cbf14b9692d8834.js"],"app":["webpack-runtime-a9e8b7badfb654e0e8a6.js","styles.1a1552db057571bb49a3.css","styles-e4fcbea169887e6398e3.js","app-0df6be084b96cb872eb8.js"],"component---gatsby-theme-gogocode-site-pages-404-tsx":["styles.1a1552db057571bb49a3.css","styles-e4fcbea169887e6398e3.js"],"component---gatsby-theme-gogocode-site-pages-index-tsx":["styles.1a1552db057571bb49a3.css","styles-e4fcbea169887e6398e3.js"],"component---gatsby-theme-gogocode-site-templates-document-tsx":["styles.1a1552db057571bb49a3.css","styles-e4fcbea169887e6398e3.js"],"component---site-pages-independent-en-tsx":["styles.1a1552db057571bb49a3.css","styles-e4fcbea169887e6398e3.js"],"component---site-pages-independent-zh-tsx":["styles.1a1552db057571bb49a3.css","styles-e4fcbea169887e6398e3.js"],"component---site-pages-index-en-tsx":["styles.1a1552db057571bb49a3.css","styles-e4fcbea169887e6398e3.js"],"component---site-pages-index-zh-tsx":["styles.1a1552db057571bb49a3.css","styles-e4fcbea169887e6398e3.js"]},"childAssetsByChunkName":{}}