{"namedChunkGroups":{"polyfill":{"name":"polyfill","assets":[{"name":"webpack-runtime-0db6163d0331ceb24129.js","size":4935},{"name":"polyfill-a3860cbf14b9692d8834.js","size":82188}],"filteredAssets":0,"assetsSize":87123,"filteredAuxiliaryAssets":0,"auxiliaryAssetsSize":0},"app":{"name":"app","assets":[{"name":"webpack-runtime-0db6163d0331ceb24129.js","size":4935},{"name":"styles.5fe2c69e003e18388dba.css","size":371582},{"name":"styles-dc8ce8716450d5b0b166.js","size":8132394},{"name":"app-1b0282c93cda274e114a.js","size":2542049}],"filteredAssets":0,"assetsSize":11050960,"filteredAuxiliaryAssets":2,"auxiliaryAssetsSize":123816},"component---gatsby-theme-gogocode-site-pages-404-tsx":{"name":"component---gatsby-theme-gogocode-site-pages-404-tsx","assets":[{"name":"styles.5fe2c69e003e18388dba.css","size":371582},{"name":"styles-dc8ce8716450d5b0b166.js","size":8132394}],"filteredAssets":0,"assetsSize":8503976,"filteredAuxiliaryAssets":2,"auxiliaryAssetsSize":123816},"component---gatsby-theme-gogocode-site-pages-index-tsx":{"name":"component---gatsby-theme-gogocode-site-pages-index-tsx","assets":[{"name":"styles.5fe2c69e003e18388dba.css","size":371582},{"name":"styles-dc8ce8716450d5b0b166.js","size":8132394}],"filteredAssets":0,"assetsSize":8503976,"filteredAuxiliaryAssets":2,"auxiliaryAssetsSize":123816},"component---gatsby-theme-gogocode-site-templates-document-tsx":{"name":"component---gatsby-theme-gogocode-site-templates-document-tsx","assets":[{"name":"styles.5fe2c69e003e18388dba.css","size":371582},{"name":"styles-dc8ce8716450d5b0b166.js","size":8132394}],"filteredAssets":0,"assetsSize":8503976,"filteredAuxiliaryAssets":2,"auxiliaryAssetsSize":123816},"component---site-pages-independent-en-tsx":{"name":"component---site-pages-independent-en-tsx","assets":[{"name":"styles.5fe2c69e003e18388dba.css","size":371582},{"name":"styles-dc8ce8716450d5b0b166.js","size":8132394}],"filteredAssets":0,"assetsSize":8503976,"filteredAuxiliaryAssets":2,"auxiliaryAssetsSize":123816},"component---site-pages-independent-zh-tsx":{"name":"component---site-pages-independent-zh-tsx","assets":[{"name":"styles.5fe2c69e003e18388dba.css","size":371582},{"name":"styles-dc8ce8716450d5b0b166.js","size":8132394}],"filteredAssets":0,"assetsSize":8503976,"filteredAuxiliaryAssets":2,"auxiliaryAssetsSize":123816},"component---site-pages-index-en-tsx":{"name":"component---site-pages-index-en-tsx","assets":[{"name":"styles.5fe2c69e003e18388dba.css","size":371582},{"name":"styles-dc8ce8716450d5b0b166.js","size":8132394}],"filteredAssets":0,"assetsSize":8503976,"filteredAuxiliaryAssets":2,"auxiliaryAssetsSize":123816},"component---site-pages-index-zh-tsx":{"name":"component---site-pages-index-zh-tsx","assets":[{"name":"styles.5fe2c69e003e18388dba.css","size":371582},{"name":"styles-dc8ce8716450d5b0b166.js","size":8132394}],"filteredAssets":0,"assetsSize":8503976,"filteredAuxiliaryAssets":2,"auxiliaryAssetsSize":123816}},"assetsByChunkName":{"polyfill":["webpack-runtime-0db6163d0331ceb24129.js","polyfill-a3860cbf14b9692d8834.js"],"app":["webpack-runtime-0db6163d0331ceb24129.js","styles.5fe2c69e003e18388dba.css","styles-dc8ce8716450d5b0b166.js","app-1b0282c93cda274e114a.js"],"component---gatsby-theme-gogocode-site-pages-404-tsx":["styles.5fe2c69e003e18388dba.css","styles-dc8ce8716450d5b0b166.js"],"component---gatsby-theme-gogocode-site-pages-index-tsx":["styles.5fe2c69e003e18388dba.css","styles-dc8ce8716450d5b0b166.js"],"component---gatsby-theme-gogocode-site-templates-document-tsx":["styles.5fe2c69e003e18388dba.css","styles-dc8ce8716450d5b0b166.js"],"component---site-pages-independent-en-tsx":["styles.5fe2c69e003e18388dba.css","styles-dc8ce8716450d5b0b166.js"],"component---site-pages-independent-zh-tsx":["styles.5fe2c69e003e18388dba.css","styles-dc8ce8716450d5b0b166.js"],"component---site-pages-index-en-tsx":["styles.5fe2c69e003e18388dba.css","styles-dc8ce8716450d5b0b166.js"],"component---site-pages-index-zh-tsx":["styles.5fe2c69e003e18388dba.css","styles-dc8ce8716450d5b0b166.js"]},"childAssetsByChunkName":{}}